Workbook

Sheet Cover
A1: PORTFOLIO RECORD TRACKER
A2: Live records across Equity, Mutual Funds, FD, RD, and Bonds for Velan and Pavi
A4: SHEET | B4: PURPOSE
A5: Dashboard | B5: Combined asset-class and owner performance summary.
A6: Velan | B6: Velan's equity position register.
A7: VelanMF | B7: Velan's mutual-fund position register.
A8: Pavi | B8: Pavi's equity position register.
A9: PaviMF | B9: Pavi's mutual-fund position register.
A10: Fixed Deposits | B10: Owner-based FD register with accrued-value tracking.
A11: Recurring Deposits | B11: Monthly RD tracking with quarterly compounding.
A12: Bonds | B12: Bond purchases, coupons, market value, and P&L.
A13: Cover | B13: Workbook guide and usage summary.
A15: HOW TO USE
A16: Enter data only in the yellow input cells of the relevant register. For RD, provide the monthly deposit, dates, rate, and deposit day. For Bonds, provide purchase, coupon, maturity, and market-price details. Calculated columns feed the dedicated dashboard rows.

Sheet Dashboard
A1: PORTFOLIO DASHBOARD
A2: Equity, mutual funds, fixed deposits, recurring deposits, and bonds for Velan and Pavi
A4: TOTAL INVESTED | C4: CURRENT VALUE | E4: TODAY'S P&L | G4: TOTAL P&L
A5: 4630630.4 | C5: 4938532.5 | E5: 7622.2596 | G5: 307902.15
A8: ASSET CLASS SUMMARY
A9: ASSET CLASS | B9: POSITIONS | C9: INVESTED | D9: CURRENT VALUE | E9: TODAY'S P&L | F9: TOTAL P&L | G9: RETURN % | H9: ALLOCATION
A10: Equity | B10: 36 | C10: 3243663.4 | D10: 3471742.5 | E10: 7614.91 | F10: 228079.05 | G10: 0.070315264 | H10: 0.70047988
A11: Mutual Funds | B11: 3 | C11: 1346967 | D11: 1425473.7 | E11: 0 | F11: 78506.772 | G11: 0.058284111 | H11: 0.29088199
A12: Fixed Deposits | B12: =B21+B26 -> 0 | C12: =C21+C26 -> 0 | D12: =D21+D26 -> 0 | E12: =E21+E26 -> 0 | F12: =F21+F26 -> 0 | G12: =IFERROR(F12/C12,0) -> 0 | H12: =IFERROR(C12/C15,0) -> 0
A13: Recurring Deposits | B13: =B22+B27 -> 1 | C13: =C22+C27 -> 240000 | D13: =D22+D27 -> 243306.05 | E13: =E22+E27 -> 0 | F13: =F22+F27 -> 3306.0499 | G13: =IFERROR(F13/C13,0) -> 0.013775208 | H13: =IFERROR(C13/C15,0) -> 0.051828796
A14: Bonds | B14: =B23+B28 -> 0 | C14: =C23+C28 -> 0 | D14: =D23+D28 -> 0 | E14: =E23+E28 -> 0 | F14: =F23+F28 -> 0 | G14: =IFERROR(F14/C14,0) -> 0 | H14: =IFERROR(C14/C15,0) -> 0
A15: Combined | B15: 40 | C15: 4630630.4 | D15: 4938532.5 | E15: 7622.2596 | F15: 307902.15 | G15: 0.06649249 | H15: 1
A17: OWNER & ASSET DETAIL
A18: OWNER / ASSET | B18: POSITIONS | C18: INVESTED | D18: CURRENT VALUE | E18: TODAY'S P&L | F18: TOTAL P&L | G18: RETURN %
A19: Velan — Equity | B19: 17 | C19: 1589655.1 | D19: 1741070.6 | E19: 2970.81 | F19: 151415.47 | G19: 0.095250515
A20: Velan — Mutual Funds | B20: 2 | C20: 341982.94 | D20: 390726.48 | E20: 0 | F20: 48743.54 | G20: 0.14253208
A21: Velan — Fixed Deposits | B21: =COUNTIFS('Fixed Deposits'!A:A,"Velan",'Fixed Deposits'!D:D,">0") -> 0 | C21: =SUMIFS('Fixed Deposits'!D:D,'Fixed Deposits'!A:A,"Velan") -> 0 | D21: =SUMIFS('Fixed Deposits'!L:L,'Fixed Deposits'!A:A,"Velan") -> 0 | E21: =SUMIFS('Fixed Deposits'!N:N,'Fixed Deposits'!A:A,"Velan") -> 0 | F21: =SUMIFS('Fixed Deposits'!M:M,'Fixed Deposits'!A:A,"Velan") -> 0 | G21: =IFERROR(F21/C21,0) -> 0
A22: Velan — Recurring Deposits | B22: =COUNTIFS('Recurring Deposits'!A:A,"Velan",'Recurring Deposits'!D:D,">0") -> 0 | C22: =SUMIFS('Recurring Deposits'!J:J,'Recurring Deposits'!A:A,"Velan") -> 0 | D22: =SUMIFS('Recurring Deposits'!L:L,'Recurring Deposits'!A:A,"Velan") -> 0 | E22: =0 -> 0 | F22: =SUMIFS('Recurring Deposits'!N:N,'Recurring Deposits'!A:A,"Velan") -> 0 | G22: =IFERROR(F22/C22,0) -> 0
A23: Velan — Bonds | B23: =COUNTIFS(Bonds!A:A,"Velan",Bonds!E:E,">0") -> 0 | C23: =SUMIFS(Bonds!N:N,Bonds!A:A,"Velan") -> 0 | D23: =SUMIFS(Bonds!O:O,Bonds!A:A,"Velan")+SUMIFS(Bonds!P:P,Bonds!A:A,"Velan") -> 0 | E23: =SUMIFS(Bonds!Q:Q,Bonds!A:A,"Velan") -> 0 | F23: =SUMIFS(Bonds!R:R,Bonds!A:A,"Velan") -> 0 | G23: =IFERROR(F23/C23,0) -> 0
A24: Pavi — Equity | B24: 19 | C24: 1654008.3 | D24: 1730671.9 | E24: 4644.1 | F24: 76663.58 | G24: 0.046350178
A25: Pavi — Mutual Funds | B25: 1 | C25: 1004984 | D25: 1034747.2 | E25: 0 | F25: 29763.232 | G25: 0.029615627
A26: Pavi — Fixed Deposits | B26: =COUNTIFS('Fixed Deposits'!A:A,"Pavi",'Fixed Deposits'!D:D,">0") -> 0 | C26: =SUMIFS('Fixed Deposits'!D:D,'Fixed Deposits'!A:A,"Pavi") -> 0 | D26: =SUMIFS('Fixed Deposits'!L:L,'Fixed Deposits'!A:A,"Pavi") -> 0 | E26: =SUMIFS('Fixed Deposits'!N:N,'Fixed Deposits'!A:A,"Pavi") -> 0 | F26: =SUMIFS('Fixed Deposits'!M:M,'Fixed Deposits'!A:A,"Pavi") -> 0 | G26: =IFERROR(F26/C26,0) -> 0
A27: Pavi — Recurring Deposits | B27: =COUNTIFS('Recurring Deposits'!A:A,"Pavi",'Recurring Deposits'!D:D,">0") -> 1 | C27: =SUMIFS('Recurring Deposits'!J:J,'Recurring Deposits'!A:A,"Pavi") -> 240000 | D27: =SUMIFS('Recurring Deposits'!L:L,'Recurring Deposits'!A:A,"Pavi") -> 243306.05 | E27: =0 -> 0 | F27: =SUMIFS('Recurring Deposits'!N:N,'Recurring Deposits'!A:A,"Pavi") -> 3306.0499 | G27: =IFERROR(F27/C27,0) -> 0.013775208
A28: Pavi — Bonds | B28: =COUNTIFS(Bonds!A:A,"Pavi",Bonds!E:E,">0") -> 0 | C28: =SUMIFS(Bonds!N:N,Bonds!A:A,"Pavi") -> 0 | D28: =SUMIFS(Bonds!O:O,Bonds!A:A,"Pavi")+SUMIFS(Bonds!P:P,Bonds!A:A,"Pavi") -> 0 | E28: =SUMIFS(Bonds!Q:Q,Bonds!A:A,"Pavi") -> 0 | F28: =SUMIFS(Bonds!R:R,Bonds!A:A,"Pavi") -> 0 | G28: =IFERROR(F28/C28,0) -> 0
A30: STORY IN BRIEF
A31: The dashboard now separates Equity, Mutual Funds, Fixed Deposits, Recurring Deposits, and Bonds. RD and Bond rows begin at zero and are linked to their owner registers; enter the required yellow input cells to populate their summaries.

Sheet Velan
A1: VELAN PORTFOLIO
A2: Enter inputs in Symbol through CMP; daily and total P&L amounts and percentages calculate automatically.
A4: Symbol | B4: Name | C4: Buy Price | D4: Quantity | E4: Previous Close | F4: CMP | G4: PL (Today) % | H4: PL (Today) | I4: PL (Total) % | J4: PL (Total)
A5: ANANTRAJ | B5: Anant Raj Ltd | C5: 578.85 | D5: 231 | E5: 587.8 | F5: 592.95 | G5: =IFERROR((VelanPortfolio[[#This Row],[CMP]]-VelanPortfolio[[#This Row],[Previous Close]])/VelanPortfolio[[#This Row],[Previous Close]],"") -> 0.0087614835 | H5: =IF(OR(VelanPortfolio[[#This Row],[CMP]]="",VelanPortfolio[[#This Row],[Previous Close]]="",VelanPortfolio[[#This Row],[Quantity]]=""),"",(VelanPortfolio[[#This Row],[CMP]]-VelanPortfolio[[#This Row],[Previous Close]])*VelanPortfolio[[#This Row],[Quantity]]) -> 1189.65 | I5: =IFERROR((VelanPortfolio[[#This Row],[CMP]]-VelanPortfolio[[#This Row],[Buy Price]])/VelanPortfolio[[#This Row],[Buy Price]],"") -> 0.024358642 | J5: =IF(OR(VelanPortfolio[[#This Row],[CMP]]="",VelanPortfolio[[#This Row],[Buy Price]]="",VelanPortfolio[[#This Row],[Quantity]]=""),"",(VelanPortfolio[[#This Row],[CMP]]-VelanPortfolio[[#This Row],[Buy Price]])*VelanPortfolio[[#This Row],[Quantity]]) -> 3257.1
A6: CHENNPETRO | B6: Chennai Petroleum Corporation Ltd | C6: 1096.8 | D6: 93 | E6: 1387 | F6: 1412.8 | G6: =IFERROR((VelanPortfolio[[#This Row],[CMP]]-VelanPortfolio[[#This Row],[Previous Close]])/VelanPortfolio[[#This Row],[Previous Close]],"") -> 0.018601298 | H6: =IF(OR(VelanPortfolio[[#This Row],[CMP]]="",VelanPortfolio[[#This Row],[Previous Close]]="",VelanPortfolio[[#This Row],[Quantity]]=""),"",(VelanPortfolio[[#This Row],[CMP]]-VelanPortfolio[[#This Row],[Previous Close]])*VelanPortfolio[[#This Row],[Quantity]]) -> 2399.4 | I6: =IFERROR((VelanPortfolio[[#This Row],[CMP]]-VelanPortfolio[[#This Row],[Buy Price]])/VelanPortfolio[[#This Row],[Buy Price]],"") -> 0.28811087 | J6: =IF(OR(VelanPortfolio[[#This Row],[CMP]]="",VelanPortfolio[[#This Row],[Buy Price]]="",VelanPortfolio[[#This Row],[Quantity]]=""),"",(VelanPortfolio[[#This Row],[CMP]]-VelanPortfolio[[#This Row],[Buy Price]])*VelanPortfolio[[#This Row],[Quantity]]) -> 29388
A7: DIXON | B7: Dixon Technologies (India) Ltd | C7: 14005 | D7: 4 | E7: 14461 | F7: 14584 | G7: =IFERROR((VelanPortfolio[[#This Row],[CMP]]-VelanPortfolio[[#This Row],[Previous Close]])/VelanPortfolio[[#This Row],[Previous Close]],"") -> 0.0085056358 | H7: =IF(OR(VelanPortfolio[[#This Row],[CMP]]="",VelanPortfolio[[#This Row],[Previous Close]]="",VelanPortfolio[[#This Row],[Quantity]]=""),"",(VelanPortfolio[[#This Row],[CMP]]-VelanPortfolio[[#This Row],[Previous Close]])*VelanPortfolio[[#This Row],[Quantity]]) -> 492 | I7: =IFERROR((VelanPortfolio[[#This Row],[CMP]]-VelanPortfolio[[#This Row],[Buy Price]])/VelanPortfolio[[#This Row],[Buy Price]],"") -> 0.041342378 | J7: =IF(OR(VelanPortfolio[[#This Row],[CMP]]="",VelanPortfolio[[#This Row],[Buy Price]]="",VelanPortfolio[[#This Row],[Quantity]]=""),"",(VelanPortfolio[[#This Row],[CMP]]-VelanPortfolio[[#This Row],[Buy Price]])*VelanPortfolio[[#This Row],[Quantity]]) -> 2316
A8: HCLTECH | B8: HCL Technologies Ltd | C8: 1355.45 | D8: 8 | E8: 1351.4 | F8: 1330 | G8: =IFERROR((VelanPortfolio[[#This Row],[CMP]]-VelanPortfolio[[#This Row],[Previous Close]])/VelanPortfolio[[#This Row],[Previous Close]],"") -> -0.01583543 | H8: =IF(OR(VelanPortfolio[[#This Row],[CMP]]="",VelanPortfolio[[#This Row],[Previous Close]]="",VelanPortfolio[[#This Row],[Quantity]]=""),"",(VelanPortfolio[[#This Row],[CMP]]-VelanPortfolio[[#This Row],[Previous Close]])*VelanPortfolio[[#This Row],[Quantity]]) -> -171.2 | I8: =IFERROR((VelanPortfolio[[#This Row],[CMP]]-VelanPortfolio[[#This Row],[Buy Price]])/VelanPortfolio[[#This Row],[Buy Price]],"") -> -0.018776052 | J8: =IF(OR(VelanPortfolio[[#This Row],[CMP]]="",VelanPortfolio[[#This Row],[Buy Price]]="",VelanPortfolio[[#This Row],[Quantity]]=""),"",(VelanPortfolio[[#This Row],[CMP]]-VelanPortfolio[[#This Row],[Buy Price]])*VelanPortfolio[[#This Row],[Quantity]]) -> -203.6
A9: HDBFS | B9: HDB Financial Services Ltd | C9: 740 | D9: 25 | E9: 675.3 | F9: 675.95 | G9: =IFERROR((VelanPortfolio[[#This Row],[CMP]]-VelanPortfolio[[#This Row],[Previous Close]])/VelanPortfolio[[#This Row],[Previous Close]],"") -> 0.00096253517 | H9: =IF(OR(VelanPortfolio[[#This Row],[CMP]]="",VelanPortfolio[[#This Row],[Previous Close]]="",VelanPortfolio[[#This Row],[Quantity]]=""),"",(VelanPortfolio[[#This Row],[CMP]]-VelanPortfolio[[#This Row],[Previous Close]])*VelanPortfolio[[#This Row],[Quantity]]) -> 16.25 | I9: =IFERROR((VelanPortfolio[[#This Row],[CMP]]-VelanPortfolio[[#This Row],[Buy Price]])/VelanPortfolio[[#This Row],[Buy Price]],"") -> -0.086554054 | J9: =IF(OR(VelanPortfolio[[#This Row],[CMP]]="",VelanPortfolio[[#This Row],[Buy Price]]="",VelanPortfolio[[#This Row],[Quantity]]=""),"",(VelanPortfolio[[#This Row],[CMP]]-VelanPortfolio[[#This Row],[Buy Price]])*VelanPortfolio[[#This Row],[Quantity]]) -> -1601.25
A10: IDFCFIRSTB | B10: IDFC First Bank Ltd | C10: 75.85 | D10: 1087 | E10: 84.9 | F10: 84.95 | G10: =IFERROR((VelanPortfolio[[#This Row],[CMP]]-VelanPortfolio[[#This Row],[Previous Close]])/VelanPortfolio[[#This Row],[Previous Close]],"") -> 0.00058892815 | H10: =IF(OR(VelanPortfolio[[#This Row],[CMP]]="",VelanPortfolio[[#This Row],[Previous Close]]="",VelanPortfolio[[#This Row],[Quantity]]=""),"",(VelanPortfolio[[#This Row],[CMP]]-VelanPortfolio[[#This Row],[Previous Close]])*VelanPortfolio[[#This Row],[Quantity]]) -> 54.35 | I10: =IFERROR((VelanPortfolio[[#This Row],[CMP]]-VelanPortfolio[[#This Row],[Buy Price]])/VelanPortfolio[[#This Row],[Buy Price]],"") -> 0.11997363 | J10: =IF(OR(VelanPortfolio[[#This Row],[CMP]]="",VelanPortfolio[[#This Row],[Buy Price]]="",VelanPortfolio[[#This Row],[Quantity]]=""),"",(VelanPortfolio[[#This Row],[CMP]]-VelanPortfolio[[#This Row],[Buy Price]])*VelanPortfolio[[#This Row],[Quantity]]) -> 9891.7
A11: ITCHOTELS | B11: ITC Hotels Ltd | C11: 615.18 | D11: 1 | E11: 161.58 | F11: 158.72 | G11: =IFERROR((VelanPortfolio[[#This Row],[CMP]]-VelanPortfolio[[#This Row],[Previous Close]])/VelanPortfolio[[#This Row],[Previous Close]],"") -> -0.01770021 | H11: =IF(OR(VelanPortfolio[[#This Row],[CMP]]="",VelanPortfolio[[#This Row],[Previous Close]]="",VelanPortfolio[[#This Row],[Quantity]]=""),"",(VelanPortfolio[[#This Row],[CMP]]-VelanPortfolio[[#This Row],[Previous Close]])*VelanPortfolio[[#This Row],[Quantity]]) -> -2.86 | I11: =IFERROR((VelanPortfolio[[#This Row],[CMP]]-VelanPortfolio[[#This Row],[Buy Price]])/VelanPortfolio[[#This Row],[Buy Price]],"") -> -0.74199421 | J11: =IF(OR(VelanPortfolio[[#This Row],[CMP]]="",VelanPortfolio[[#This Row],[Buy Price]]="",VelanPortfolio[[#This Row],[Quantity]]=""),"",(VelanPortfolio[[#This Row],[CMP]]-VelanPortfolio[[#This Row],[Buy Price]])*VelanPortfolio[[#This Row],[Quantity]]) -> -456.46
A12: KTKBANK | B12: Karnataka Bank Ltd | C12: 278.64 | D12: 530 | E12: 330.9 | F12: 329.4 | G12: =IFERROR((VelanPortfolio[[#This Row],[CMP]]-VelanPortfolio[[#This Row],[Previous Close]])/VelanPortfolio[[#This Row],[Previous Close]],"") -> -0.0045330916 | H12: =IF(OR(VelanPortfolio[[#This Row],[CMP]]="",VelanPortfolio[[#This Row],[Previous Close]]="",VelanPortfolio[[#This Row],[Quantity]]=""),"",(VelanPortfolio[[#This Row],[CMP]]-VelanPortfolio[[#This Row],[Previous Close]])*VelanPortfolio[[#This Row],[Quantity]]) -> -795 | I12: =IFERROR((VelanPortfolio[[#This Row],[CMP]]-VelanPortfolio[[#This Row],[Buy Price]])/VelanPortfolio[[#This Row],[Buy Price]],"") -> 0.18217054 | J12: =IF(OR(VelanPortfolio[[#This Row],[CMP]]="",VelanPortfolio[[#This Row],[Buy Price]]="",VelanPortfolio[[#This Row],[Quantity]]=""),"",(VelanPortfolio[[#This Row],[CMP]]-VelanPortfolio[[#This Row],[Buy Price]])*VelanPortfolio[[#This Row],[Quantity]]) -> 26902.8
A13: MODEFENCE | B13: Motilal Oswal Nifty India Defence ETF | C13: 99.07 | D13: 538 | E13: 105.72 | F13: 105.01 | G13: =IFERROR((VelanPortfolio[[#This Row],[CMP]]-VelanPortfolio[[#This Row],[Previous Close]])/VelanPortfolio[[#This Row],[Previous Close]],"") -> -0.0067158532 | H13: =IF(OR(VelanPortfolio[[#This Row],[CMP]]="",VelanPortfolio[[#This Row],[Previous Close]]="",VelanPortfolio[[#This Row],[Quantity]]=""),"",(VelanPortfolio[[#This Row],[CMP]]-VelanPortfolio[[#This Row],[Previous Close]])*VelanPortfolio[[#This Row],[Quantity]]) -> -381.98 | I13: =IFERROR((VelanPortfolio[[#This Row],[CMP]]-VelanPortfolio[[#This Row],[Buy Price]])/VelanPortfolio[[#This Row],[Buy Price]],"") -> 0.059957606 | J13: =IF(OR(VelanPortfolio[[#This Row],[CMP]]="",VelanPortfolio[[#This Row],[Buy Price]]="",VelanPortfolio[[#This Row],[Quantity]]=""),"",(VelanPortfolio[[#This Row],[CMP]]-VelanPortfolio[[#This Row],[Buy Price]])*VelanPortfolio[[#This Row],[Quantity]]) -> 3195.72
A14: NATCOPHARM | B14: Natco Pharma Ltd | C14: 936.15 | D14: 65 | E14: 849.2 | F14: 841.85 | G14: =IFERROR((VelanPortfolio[[#This Row],[CMP]]-VelanPortfolio[[#This Row],[Previous Close]])/VelanPortfolio[[#This Row],[Previous Close]],"") -> -0.0086552049 | H14: =IF(OR(VelanPortfolio[[#This Row],[CMP]]="",VelanPortfolio[[#This Row],[Previous Close]]="",VelanPortfolio[[#This Row],[Quantity]]=""),"",(VelanPortfolio[[#This Row],[CMP]]-VelanPortfolio[[#This Row],[Previous Close]])*VelanPortfolio[[#This Row],[Quantity]]) -> -477.75 | I14: =IFERROR((VelanPortfolio[[#This Row],[CMP]]-VelanPortfolio[[#This Row],[Buy Price]])/VelanPortfolio[[#This Row],[Buy Price]],"") -> -0.10073172 | J14: =IF(OR(VelanPortfolio[[#This Row],[CMP]]="",VelanPortfolio[[#This Row],[Buy Price]]="",VelanPortfolio[[#This Row],[Quantity]]=""),"",(VelanPortfolio[[#This Row],[CMP]]-VelanPortfolio[[#This Row],[Buy Price]])*VelanPortfolio[[#This Row],[Quantity]]) -> -6129.5
A15: NETWEB | B15: Netweb Technologies India Ltd | C15: 5098.49 | D15: 40 | E15: 5136.5 | F15: 5120 | G15: =IFERROR((VelanPortfolio[[#This Row],[CMP]]-VelanPortfolio[[#This Row],[Previous Close]])/VelanPortfolio[[#This Row],[Previous Close]],"") -> -0.0032123041 | H15: =IF(OR(VelanPortfolio[[#This Row],[CMP]]="",VelanPortfolio[[#This Row],[Previous Close]]="",VelanPortfolio[[#This Row],[Quantity]]=""),"",(VelanPortfolio[[#This Row],[CMP]]-VelanPortfolio[[#This Row],[Previous Close]])*VelanPortfolio[[#This Row],[Quantity]]) -> -660 | I15: =IFERROR((VelanPortfolio[[#This Row],[CMP]]-VelanPortfolio[[#This Row],[Buy Price]])/VelanPortfolio[[#This Row],[Buy Price]],"") -> 0.0042188962 | J15: =IF(OR(VelanPortfolio[[#This Row],[CMP]]="",VelanPortfolio[[#This Row],[Buy Price]]="",VelanPortfolio[[#This Row],[Quantity]]=""),"",(VelanPortfolio[[#This Row],[CMP]]-VelanPortfolio[[#This Row],[Buy Price]])*VelanPortfolio[[#This Row],[Quantity]]) -> 860.4
A16: OIL | B16: Oil India Ltd | C16: 468.28 | D16: 472 | E16: 490 | F16: 498 | G16: =IFERROR((VelanPortfolio[[#This Row],[CMP]]-VelanPortfolio[[#This Row],[Previous Close]])/VelanPortfolio[[#This Row],[Previous Close]],"") -> 0.016326531 | H16: =IF(OR(VelanPortfolio[[#This Row],[CMP]]="",VelanPortfolio[[#This Row],[Previous Close]]="",VelanPortfolio[[#This Row],[Quantity]]=""),"",(VelanPortfolio[[#This Row],[CMP]]-VelanPortfolio[[#This Row],[Previous Close]])*VelanPortfolio[[#This Row],[Quantity]]) -> 3776 | I16: =IFERROR((VelanPortfolio[[#This Row],[CMP]]-VelanPortfolio[[#This Row],[Buy Price]])/VelanPortfolio[[#This Row],[Buy Price]],"") -> 0.063466302 | J16: =IF(OR(VelanPortfolio[[#This Row],[CMP]]="",VelanPortfolio[[#This Row],[Buy Price]]="",VelanPortfolio[[#This Row],[Quantity]]=""),"",(VelanPortfolio[[#This Row],[CMP]]-VelanPortfolio[[#This Row],[Buy Price]])*VelanPortfolio[[#This Row],[Quantity]]) -> 14027.84
... A21: TMCV | B21: Tata Motors Ltd | C21: 328.71 | D21: 258 | E21: 464.35 | F21: 446 | G21: =IFERROR((VelanPortfolio[[#This Row],[CMP]]-VelanPortfolio[[#This Row],[Previous Close]])/VelanPortfolio[[#This Row],[Previous Close]],"") -> -0.039517605 | H21: =IF(OR(VelanPortfolio[[#This Row],[CMP]]="",VelanPortfolio[[#This Row],[Previous Close]]="",VelanPortfolio[[#This Row],[Quantity]]=""),"",(VelanPortfolio[[#This Row],[CMP]]-VelanPortfolio[[#This Row],[Previous Close]])*VelanPortfolio[[#This Row],[Quantity]]) -> -4734.3 | I21: =IFERROR((VelanPortfolio[[#This Row],[CMP]]-VelanPortfolio[[#This Row],[Buy Price]])/VelanPortfolio[[#This Row],[Buy Price]],"") -> 0.35681908 | J21: =IF(OR(VelanPortfolio[[#This Row],[CMP]]="",VelanPortfolio[[#This Row],[Buy Price]]="",VelanPortfolio[[#This Row],[Quantity]]=""),"",(VelanPortfolio[[#This Row],[CMP]]-VelanPortfolio[[#This Row],[Buy Price]])*VelanPortfolio[[#This Row],[Quantity]]) -> 30260.82

Sheet Pavi
A1: PAVI PORTFOLIO
A2: Enter inputs in Symbol through CMP; daily and total P&L amounts and percentages calculate automatically.
A4: Symbol | B4: Name | C4: Buy Price | D4: Quantity | E4: Previous Close | F4: CMP | G4: PL (Today) % | H4: PL (Today) | I4: PL (Total) % | J4: PL (Total)
A5: ANANTRAJ | B5: Anant Raj Ltd | C5: 612.26 | D5: 125 | E5: 587.8 | F5: 592.95 | G5: =IFERROR((PaviPortfolio[[#This Row],[CMP]]-PaviPortfolio[[#This Row],[Previous Close]])/PaviPortfolio[[#This Row],[Previous Close]],"") -> 0.0087614835 | H5: =IF(OR(PaviPortfolio[[#This Row],[CMP]]="",PaviPortfolio[[#This Row],[Previous Close]]="",PaviPortfolio[[#This Row],[Quantity]]=""),"",(PaviPortfolio[[#This Row],[CMP]]-PaviPortfolio[[#This Row],[Previous Close]])*PaviPortfolio[[#This Row],[Quantity]]) -> 643.75 | I5: =IFERROR((PaviPortfolio[[#This Row],[CMP]]-PaviPortfolio[[#This Row],[Buy Price]])/PaviPortfolio[[#This Row],[Buy Price]],"") -> -0.031538889 | J5: =IF(OR(PaviPortfolio[[#This Row],[CMP]]="",PaviPortfolio[[#This Row],[Buy Price]]="",PaviPortfolio[[#This Row],[Quantity]]=""),"",(PaviPortfolio[[#This Row],[CMP]]-PaviPortfolio[[#This Row],[Buy Price]])*PaviPortfolio[[#This Row],[Quantity]]) -> -2413.75
A6: ANGELONE | B6: Angel One Ltd | C6: 279.08 | D6: 380 | E6: 281.55 | F6: 279 | G6: =IFERROR((PaviPortfolio[[#This Row],[CMP]]-PaviPortfolio[[#This Row],[Previous Close]])/PaviPortfolio[[#This Row],[Previous Close]],"") -> -0.0090570059 | H6: =IF(OR(PaviPortfolio[[#This Row],[CMP]]="",PaviPortfolio[[#This Row],[Previous Close]]="",PaviPortfolio[[#This Row],[Quantity]]=""),"",(PaviPortfolio[[#This Row],[CMP]]-PaviPortfolio[[#This Row],[Previous Close]])*PaviPortfolio[[#This Row],[Quantity]]) -> -969 | I6: =IFERROR((PaviPortfolio[[#This Row],[CMP]]-PaviPortfolio[[#This Row],[Buy Price]])/PaviPortfolio[[#This Row],[Buy Price]],"") -> -0.00028665616 | J6: =IF(OR(PaviPortfolio[[#This Row],[CMP]]="",PaviPortfolio[[#This Row],[Buy Price]]="",PaviPortfolio[[#This Row],[Quantity]]=""),"",(PaviPortfolio[[#This Row],[CMP]]-PaviPortfolio[[#This Row],[Buy Price]])*PaviPortfolio[[#This Row],[Quantity]]) -> -30.4
A7: AUTOBEES | B7: Nippon India Nifty Auto ETF | C7: 283.63 | D7: 111 | E7: 292.63 | F7: 288.01 | G7: =IFERROR((PaviPortfolio[[#This Row],[CMP]]-PaviPortfolio[[#This Row],[Previous Close]])/PaviPortfolio[[#This Row],[Previous Close]],"") -> -0.015787855 | H7: =IF(OR(PaviPortfolio[[#This Row],[CMP]]="",PaviPortfolio[[#This Row],[Previous Close]]="",PaviPortfolio[[#This Row],[Quantity]]=""),"",(PaviPortfolio[[#This Row],[CMP]]-PaviPortfolio[[#This Row],[Previous Close]])*PaviPortfolio[[#This Row],[Quantity]]) -> -512.82 | I7: =IFERROR((PaviPortfolio[[#This Row],[CMP]]-PaviPortfolio[[#This Row],[Buy Price]])/PaviPortfolio[[#This Row],[Buy Price]],"") -> 0.015442654 | J7: =IF(OR(PaviPortfolio[[#This Row],[CMP]]="",PaviPortfolio[[#This Row],[Buy Price]]="",PaviPortfolio[[#This Row],[Quantity]]=""),"",(PaviPortfolio[[#This Row],[CMP]]-PaviPortfolio[[#This Row],[Buy Price]])*PaviPortfolio[[#This Row],[Quantity]]) -> 486.18
A8: BANKBEES | B8: Nippon India Etf Nifty Bank Bees | C8: 612.75 | D8: 111 | E8: 593.79 | F8: 593.43 | G8: =IFERROR((PaviPortfolio[[#This Row],[CMP]]-PaviPortfolio[[#This Row],[Previous Close]])/PaviPortfolio[[#This Row],[Previous Close]],"") -> -0.00060627495 | H8: =IF(OR(PaviPortfolio[[#This Row],[CMP]]="",PaviPortfolio[[#This Row],[Previous Close]]="",PaviPortfolio[[#This Row],[Quantity]]=""),"",(PaviPortfolio[[#This Row],[CMP]]-PaviPortfolio[[#This Row],[Previous Close]])*PaviPortfolio[[#This Row],[Quantity]]) -> -39.96 | I8: =IFERROR((PaviPortfolio[[#This Row],[CMP]]-PaviPortfolio[[#This Row],[Buy Price]])/PaviPortfolio[[#This Row],[Buy Price]],"") -> -0.031529988 | J8: =IF(OR(PaviPortfolio[[#This Row],[CMP]]="",PaviPortfolio[[#This Row],[Buy Price]]="",PaviPortfolio[[#This Row],[Quantity]]=""),"",(PaviPortfolio[[#This Row],[CMP]]-PaviPortfolio[[#This Row],[Buy Price]])*PaviPortfolio[[#This Row],[Quantity]]) -> -2144.52
A9: COALINDIA | B9: Coal India Limited | C9: 417.17 | D9: 277 | E9: 401.6 | F9: 416.3 | G9: =IFERROR((PaviPortfolio[[#This Row],[CMP]]-PaviPortfolio[[#This Row],[Previous Close]])/PaviPortfolio[[#This Row],[Previous Close]],"") -> 0.036603586 | H9: =IF(OR(PaviPortfolio[[#This Row],[CMP]]="",PaviPortfolio[[#This Row],[Previous Close]]="",PaviPortfolio[[#This Row],[Quantity]]=""),"",(PaviPortfolio[[#This Row],[CMP]]-PaviPortfolio[[#This Row],[Previous Close]])*PaviPortfolio[[#This Row],[Quantity]]) -> 4071.9 | I9: =IFERROR((PaviPortfolio[[#This Row],[CMP]]-PaviPortfolio[[#This Row],[Buy Price]])/PaviPortfolio[[#This Row],[Buy Price]],"") -> -0.0020854807 | J9: =IF(OR(PaviPortfolio[[#This Row],[CMP]]="",PaviPortfolio[[#This Row],[Buy Price]]="",PaviPortfolio[[#This Row],[Quantity]]=""),"",(PaviPortfolio[[#This Row],[CMP]]-PaviPortfolio[[#This Row],[Buy Price]])*PaviPortfolio[[#This Row],[Quantity]]) -> -240.99
A10: DIXON | B10: Dixon Technologies (India) Ltd | C10: 12907.29 | D10: 17 | E10: 14461 | F10: 14584 | G10: =IFERROR((PaviPortfolio[[#This Row],[CMP]]-PaviPortfolio[[#This Row],[Previous Close]])/PaviPortfolio[[#This Row],[Previous Close]],"") -> 0.0085056358 | H10: =IF(OR(PaviPortfolio[[#This Row],[CMP]]="",PaviPortfolio[[#This Row],[Previous Close]]="",PaviPortfolio[[#This Row],[Quantity]]=""),"",(PaviPortfolio[[#This Row],[CMP]]-PaviPortfolio[[#This Row],[Previous Close]])*PaviPortfolio[[#This Row],[Quantity]]) -> 2091 | I10: =IFERROR((PaviPortfolio[[#This Row],[CMP]]-PaviPortfolio[[#This Row],[Buy Price]])/PaviPortfolio[[#This Row],[Buy Price]],"") -> 0.12990411 | J10: =IF(OR(PaviPortfolio[[#This Row],[CMP]]="",PaviPortfolio[[#This Row],[Buy Price]]="",PaviPortfolio[[#This Row],[Quantity]]=""),"",(PaviPortfolio[[#This Row],[CMP]]-PaviPortfolio[[#This Row],[Buy Price]])*PaviPortfolio[[#This Row],[Quantity]]) -> 28504.07
A11: GOLDBEES | B11: Nippon India ETF Gold BeES | C11: 86.88 | D11: 865 | E11: 125.34 | F11: 123.57 | G11: =IFERROR((PaviPortfolio[[#This Row],[CMP]]-PaviPortfolio[[#This Row],[Previous Close]])/PaviPortfolio[[#This Row],[Previous Close]],"") -> -0.014121589 | H11: =IF(OR(PaviPortfolio[[#This Row],[CMP]]="",PaviPortfolio[[#This Row],[Previous Close]]="",PaviPortfolio[[#This Row],[Quantity]]=""),"",(PaviPortfolio[[#This Row],[CMP]]-PaviPortfolio[[#This Row],[Previous Close]])*PaviPortfolio[[#This Row],[Quantity]]) -> -1531.05 | I11: =IFERROR((PaviPortfolio[[#This Row],[CMP]]-PaviPortfolio[[#This Row],[Buy Price]])/PaviPortfolio[[#This Row],[Buy Price]],"") -> 0.42230663 | J11: =IF(OR(PaviPortfolio[[#This Row],[CMP]]="",PaviPortfolio[[#This Row],[Buy Price]]="",PaviPortfolio[[#This Row],[Quantity]]=""),"",(PaviPortfolio[[#This Row],[CMP]]-PaviPortfolio[[#This Row],[Buy Price]])*PaviPortfolio[[#This Row],[Quantity]]) -> 31736.85
A12: HAL | B12: Hindustan Aeronautics Ltd | C12: 4613.56 | D12: 15 | E12: 4807.6 | F12: 4776.5 | G12: =IFERROR((PaviPortfolio[[#This Row],[CMP]]-PaviPortfolio[[#This Row],[Previous Close]])/PaviPortfolio[[#This Row],[Previous Close]],"") -> -0.0064689242 | H12: =IF(OR(PaviPortfolio[[#This Row],[CMP]]="",PaviPortfolio[[#This Row],[Previous Close]]="",PaviPortfolio[[#This Row],[Quantity]]=""),"",(PaviPortfolio[[#This Row],[CMP]]-PaviPortfolio[[#This Row],[Previous Close]])*PaviPortfolio[[#This Row],[Quantity]]) -> -466.5 | I12: =IFERROR((PaviPortfolio[[#This Row],[CMP]]-PaviPortfolio[[#This Row],[Buy Price]])/PaviPortfolio[[#This Row],[Buy Price]],"") -> 0.035317629 | J12: =IF(OR(PaviPortfolio[[#This Row],[CMP]]="",PaviPortfolio[[#This Row],[Buy Price]]="",PaviPortfolio[[#This Row],[Quantity]]=""),"",(PaviPortfolio[[#This Row],[CMP]]-PaviPortfolio[[#This Row],[Buy Price]])*PaviPortfolio[[#This Row],[Quantity]]) -> 2444.1
A13: HCLTECH | B13: HCL Technologies Ltd | C13: 1241.36 | D13: 80 | E13: 1351.4 | F13: 1330 | G13: =IFERROR((PaviPortfolio[[#This Row],[CMP]]-PaviPortfolio[[#This Row],[Previous Close]])/PaviPortfolio[[#This Row],[Previous Close]],"") -> -0.01583543 | H13: =IF(OR(PaviPortfolio[[#This Row],[CMP]]="",PaviPortfolio[[#This Row],[Previous Close]]="",PaviPortfolio[[#This Row],[Quantity]]=""),"",(PaviPortfolio[[#This Row],[CMP]]-PaviPortfolio[[#This Row],[Previous Close]])*PaviPortfolio[[#This Row],[Quantity]]) -> -1712 | I13: =IFERROR((PaviPortfolio[[#This Row],[CMP]]-PaviPortfolio[[#This Row],[Buy Price]])/PaviPortfolio[[#This Row],[Buy Price]],"") -> 0.071405555 | J13: =IF(OR(PaviPortfolio[[#This Row],[CMP]]="",PaviPortfolio[[#This Row],[Buy Price]]="",PaviPortfolio[[#This Row],[Quantity]]=""),"",(PaviPortfolio[[#This Row],[CMP]]-PaviPortfolio[[#This Row],[Buy Price]])*PaviPortfolio[[#This Row],[Quantity]]) -> 7091.2
A14: ITCHOTELS | B14: ITC Hotels Ltd | C14: 593.77 | D14: 17 | E14: 161.58 | F14: 158.72 | G14: =IFERROR((PaviPortfolio[[#This Row],[CMP]]-PaviPortfolio[[#This Row],[Previous Close]])/PaviPortfolio[[#This Row],[Previous Close]],"") -> -0.01770021 | H14: =IF(OR(PaviPortfolio[[#This Row],[CMP]]="",PaviPortfolio[[#This Row],[Previous Close]]="",PaviPortfolio[[#This Row],[Quantity]]=""),"",(PaviPortfolio[[#This Row],[CMP]]-PaviPortfolio[[#This Row],[Previous Close]])*PaviPortfolio[[#This Row],[Quantity]]) -> -48.62 | I14: =IFERROR((PaviPortfolio[[#This Row],[CMP]]-PaviPortfolio[[#This Row],[Buy Price]])/PaviPortfolio[[#This Row],[Buy Price]],"") -> -0.73269111 | J14: =IF(OR(PaviPortfolio[[#This Row],[CMP]]="",PaviPortfolio[[#This Row],[Buy Price]]="",PaviPortfolio[[#This Row],[Quantity]]=""),"",(PaviPortfolio[[#This Row],[CMP]]-PaviPortfolio[[#This Row],[Buy Price]])*PaviPortfolio[[#This Row],[Quantity]]) -> -7395.85
A15: JSWENERGY | B15: JSW Energy Ltd | C15: 556.1 | D15: 151 | E15: 518 | F15: 539 | G15: =IFERROR((PaviPortfolio[[#This Row],[CMP]]-PaviPortfolio[[#This Row],[Previous Close]])/PaviPortfolio[[#This Row],[Previous Close]],"") -> 0.040540541 | H15: =IF(OR(PaviPortfolio[[#This Row],[CMP]]="",PaviPortfolio[[#This Row],[Previous Close]]="",PaviPortfolio[[#This Row],[Quantity]]=""),"",(PaviPortfolio[[#This Row],[CMP]]-PaviPortfolio[[#This Row],[Previous Close]])*PaviPortfolio[[#This Row],[Quantity]]) -> 3171 | I15: =IFERROR((PaviPortfolio[[#This Row],[CMP]]-PaviPortfolio[[#This Row],[Buy Price]])/PaviPortfolio[[#This Row],[Buy Price]],"") -> -0.030749865 | J15: =IF(OR(PaviPortfolio[[#This Row],[CMP]]="",PaviPortfolio[[#This Row],[Buy Price]]="",PaviPortfolio[[#This Row],[Quantity]]=""),"",(PaviPortfolio[[#This Row],[CMP]]-PaviPortfolio[[#This Row],[Buy Price]])*PaviPortfolio[[#This Row],[Quantity]]) -> -2582.1
A16: MODEFENCE | B16: Motilal Oswal Nifty India Defence ETF | C16: 93.13 | D16: 1430 | E16: 105.72 | F16: 105.01 | G16: =IFERROR((PaviPortfolio[[#This Row],[CMP]]-PaviPortfolio[[#This Row],[Previous Close]])/PaviPortfolio[[#This Row],[Previous Close]],"") -> -0.0067158532 | H16: =IF(OR(PaviPortfolio[[#This Row],[CMP]]="",PaviPortfolio[[#This Row],[Previous Close]]="",PaviPortfolio[[#This Row],[Quantity]]=""),"",(PaviPortfolio[[#This Row],[CMP]]-PaviPortfolio[[#This Row],[Previous Close]])*PaviPortfolio[[#This Row],[Quantity]]) -> -1015.3 | I16: =IFERROR((PaviPortfolio[[#This Row],[CMP]]-PaviPortfolio[[#This Row],[Buy Price]])/PaviPortfolio[[#This Row],[Buy Price]],"") -> 0.12756362 | J16: =IF(OR(PaviPortfolio[[#This Row],[CMP]]="",PaviPortfolio[[#This Row],[Buy Price]]="",PaviPortfolio[[#This Row],[Quantity]]=""),"",(PaviPortfolio[[#This Row],[CMP]]-PaviPortfolio[[#This Row],[Buy Price]])*PaviPortfolio[[#This Row],[Quantity]]) -> 16988.4
... A23: WABAG | B23: VA Tech Wabag Ltd | C23: 2017.68 | D23: 25 | E23: 2013.9 | F23: 1994 | G23: =IFERROR((PaviPortfolio[[#This Row],[CMP]]-PaviPortfolio[[#This Row],[Previous Close]])/PaviPortfolio[[#This Row],[Previous Close]],"") -> -0.0098813248 | H23: =IF(OR(PaviPortfolio[[#This Row],[CMP]]="",PaviPortfolio[[#This Row],[Previous Close]]="",PaviPortfolio[[#This Row],[Quantity]]=""),"",(PaviPortfolio[[#This Row],[CMP]]-PaviPortfolio[[#This Row],[Previous Close]])*PaviPortfolio[[#This Row],[Quantity]]) -> -497.5 | I23: =IFERROR((PaviPortfolio[[#This Row],[CMP]]-PaviPortfolio[[#This Row],[Buy Price]])/PaviPortfolio[[#This Row],[Buy Price]],"") -> -0.011736252 | J23: =IF(OR(PaviPortfolio[[#This Row],[CMP]]="",PaviPortfolio[[#This Row],[Buy Price]]="",PaviPortfolio[[#This Row],[Quantity]]=""),"",(PaviPortfolio[[#This Row],[CMP]]-PaviPortfolio[[#This Row],[Buy Price]])*PaviPortfolio[[#This Row],[Quantity]]) -> -592

Sheet VelanMF
A1: VELAN MUTUAL FUND PORTFOLIO
A2: Enter Symbol, Name, Buy Price, Previous Close, CMP, and Quantity; P&L calculates automatically.
A4: Symbol | B4: Name | C4: Buy Price | D4: Previous Close | E4: CMP | F4: Quantity | G4: PL (Today) | H4: PL (Total)
A5: TATA_ARBI_DIR_18P1ZST | B5: =IFERROR(__xludf.DUMMYFUNCTION("GOOGLEFINANCE(""MUTF_IN:""&A5,""NAME"")"),"Tata Arbitrage Fund Direct Growth") -> Tata Arbitrage Fund Direct Growth | C5: 15.88 | D5: =IFERROR(__xludf.DUMMYFUNCTION("GOOGLEFINANCE(""MUTF_IN:""&A5,""closeyest"")"),16.34) -> 16.34 | E5: =IFERROR(__xludf.DUMMYFUNCTION("GOOGLEFINANCE(""MUTF_IN:""&A5,""price"")"),16.34) -> 16.34 | F5: 18985.206 | G5: =IF(OR(VelanMF!$D5="",VelanMF!$E5="",VelanMF!$F5=""),"",(VelanMF!$E5-VelanMF!$D5)*VelanMF!$F5) -> 0 | H5: =IF(OR(VelanMF!$C5="",VelanMF!$E5="",VelanMF!$F5=""),"",(VelanMF!$E5-VelanMF!$C5)*VelanMF!$F5) -> 8733.1948
A6: QUAN_ELSS_TAX_KBGFAS | B6: =IFERROR(__xludf.DUMMYFUNCTION("GOOGLEFINANCE(""MUTF_IN:""&A6,""NAME"")"),"Quant ELSS Tax Saver Growth Option Direct Plan") -> Quant ELSS Tax Saver Growth Option Direct Plan | C6: 232.59 | D6: =IFERROR(__xludf.DUMMYFUNCTION("GOOGLEFINANCE(""MUTF_IN:""&A6,""closeyest"")"),462.38) -> 462.38 | E6: =IFERROR(__xludf.DUMMYFUNCTION("GOOGLEFINANCE(""MUTF_IN:""&A6,""price"")"),462.38) -> 462.38 | F6: 174.117 | G6: =IF(OR(VelanMF!$D6="",VelanMF!$E6="",VelanMF!$F6=""),"",(VelanMF!$E6-VelanMF!$D6)*VelanMF!$F6) -> 0 | H6: =IF(OR(VelanMF!$C6="",VelanMF!$E6="",VelanMF!$F6=""),"",(VelanMF!$E6-VelanMF!$C6)*VelanMF!$F6) -> 40010.345

Sheet PaviMF
A1: PAVI MUTUAL FUND PORTFOLIO
A2: Enter Symbol, Name, Buy Price, Previous Close, CMP, and Quantity; P&L calculates automatically.
A4: Symbol | B4: Name | C4: Buy Price | D4: Previous Close | E4: CMP | F4: Quantity | G4: PL (Today) | H4: PL (Total)
A5: TATA_ARBI_DIR_18P1ZST | B5: =IFERROR(__xludf.DUMMYFUNCTION("GOOGLEFINANCE(""MUTF_IN:""&A5,""NAME"")"),"Tata Arbitrage Fund Direct Growth") -> Tata Arbitrage Fund Direct Growth | C5: 15.87 | D5: =IFERROR(__xludf.DUMMYFUNCTION("GOOGLEFINANCE(""MUTF_IN:""&A5,""closeyest"")"),16.34) -> 16.34 | E5: =IFERROR(__xludf.DUMMYFUNCTION("GOOGLEFINANCE(""MUTF_IN:""&A5,""price"")"),16.34) -> 16.34 | F5: 63326.025 | G5: =IF(OR(PaviMF!$D5="",PaviMF!$E5="",PaviMF!$F5=""),"",(PaviMF!$E5-PaviMF!$D5)*PaviMF!$F5) -> 0 | H5: =IF(OR(PaviMF!$C5="",PaviMF!$E5="",PaviMF!$F5=""),"",(PaviMF!$E5-PaviMF!$C5)*PaviMF!$F5) -> 29763.232

Sheet Fixed Deposits
A1: FIXED DEPOSIT REGISTER
A2: Enter FD details for Velan and Pavi; maturity, accrued value, interest, and status calculate automatically.
A4: Owner | B4: Bank / Institution | C4: FD Number | D4: Principal | E4: Start Date | F4: Maturity Date | G4: Interest Rate | H4: Compounding Frequency | I4: Periods / Year | J4: Tenure (Days) | K4: Maturity Value | L4: Accrued Value | M4: Accrued Interest | N4: Today's Interest | O4: Status
A5: Velan | I5: =IF(H5="","",IF(H5="Simple",0,IF(H5="Monthly",12,IF(H5="Quarterly",4,IF(H5="Half-yearly",2,IF(H5="Annually",1,"")))))) | J5: =IF(OR(E5="",F5=""),"",MAX(0,F5-E5)) | K5: =IF(OR(D5="",G5="",J5="",I5=""),"",IF(I5=0,D5*(1+G5*J5/365),D5*(1+G5/I5)^(I5*J5/365))) | L5: =IF(OR(D5="",E5="",J5="",G5="",I5=""),"",IF(I5=0,D5*(1+G5*MIN(MAX(TODAY()-E5,0),J5)/365),D5*(1+G5/I5)^(I5*MIN(MAX(TODAY()-E5,0),J5)/365))) | M5: =IF(L5="","",L5-D5) | N5: =IF(OR(D5="",E5="",F5="",G5="",I5="",TODAY()<E5,TODAY()>F5),0,IF(I5=0,D5*G5/365,L5-D5*(1+G5/I5)^(I5*MAX(MIN(TODAY()-E5-1,J5),0)/365))) -> 0 | O5: =IF(A5="","",IF(OR(D5="",E5="",F5="",G5="",H5=""),"Details Required",IF(TODAY()<E5,"Upcoming",IF(TODAY()>=F5,"Matured","Active")))) -> Details Required
A6: Pavi | I6: =IF(H6="","",IF(H6="Simple",0,IF(H6="Monthly",12,IF(H6="Quarterly",4,IF(H6="Half-yearly",2,IF(H6="Annually",1,"")))))) | J6: =IF(OR(E6="",F6=""),"",MAX(0,F6-E6)) | K6: =IF(OR(D6="",G6="",J6="",I6=""),"",IF(I6=0,D6*(1+G6*J6/365),D6*(1+G6/I6)^(I6*J6/365))) | L6: =IF(OR(D6="",E6="",J6="",G6="",I6=""),"",IF(I6=0,D6*(1+G6*MIN(MAX(TODAY()-E6,0),J6)/365),D6*(1+G6/I6)^(I6*MIN(MAX(TODAY()-E6,0),J6)/365))) | M6: =IF(L6="","",L6-D6) | N6: =IF(OR(D6="",E6="",F6="",G6="",I6="",TODAY()<E6,TODAY()>F6),0,IF(I6=0,D6*G6/365,L6-D6*(1+G6/I6)^(I6*MAX(MIN(TODAY()-E6-1,J6),0)/365))) -> 0 | O6: =IF(A6="","",IF(OR(D6="",E6="",F6="",G6="",H6=""),"Details Required",IF(TODAY()<E6,"Upcoming",IF(TODAY()>=F6,"Matured","Active")))) -> Details Required

Sheet Recurring Deposits
A1: RECURRING DEPOSIT REGISTER
A2: Monthly deposits with quarterly compounding for Velan and Pavi; calculated columns update from the entered terms.
A4: Owner | B4: Bank / Institution | C4: RD Number | D4: Monthly Deposit | E4: Start Date | F4: Maturity Date | G4: Interest Rate | H4: Deposit Day | I4: Tenure (Months) | J4: Deposited to Date | K4: Total Scheduled Deposit | L4: Accrued Value | M4: Maturity Value | N4: Accrued Interest | O4: Status
A5: Velan | I5: =IF(OR(E5="",F5=""),"",MAX(0,DATEDIF(E5,F5,"m"))) | J5: =IF(OR(D5="",E5="",I5=""),"",D5*MIN(I5,MAX(0,DATEDIF(E5,MIN(TODAY(),F5),"m")+1))) | K5: =IF(OR(D5="",I5=""),"",D5*I5) | L5: =IF(OR(D5="",E5="",F5="",G5=""),"",_xlfn.LET(_xlpm.m,MIN(I5,MAX(0,DATEDIF(E5,MIN(TODAY(),F5),"m")+1)),_xlpm.rm,(1+G5/4)^(1/3)-1,IF(_xlpm.rm=0,D5*_xlpm.m,D5*((1+_xlpm.rm)^_xlpm.m-1)/_xlpm.rm))) | M5: =IF(OR(D5="",I5="",G5=""),"",_xlfn.LET(_xlpm.rm,(1+G5/4)^(1/3)-1,IF(_xlpm.rm=0,D5*I5,D5*((1+_xlpm.rm)^I5-1)/_xlpm.rm))) | N5: =IF(OR(L5="",J5=""),"",L5-J5) | O5: =IF(A5="","",IF(OR(E5="",F5=""),"Details Required",IF(TODAY()<E5,"Upcoming",IF(TODAY()>=F5,"Matured","Active")))) -> Details Required
A6: Pavi | B6: IDFC | D6: 40000 | E6: 46086 | F6: 46482 | G6: 0.066 | H6: 5 | I6: =IF(OR(E6="",F6=""),"",MAX(0,DATEDIF(E6,F6,"m"))) -> 13 | J6: =IF(OR(D6="",E6="",I6=""),"",D6*MIN(I6,MAX(0,DATEDIF(E6,MIN(TODAY(),F6),"m")+1))) -> 240000 | K6: =IF(OR(D6="",I6=""),"",D6*I6) -> 520000 | L6: =IF(OR(D6="",E6="",F6="",G6=""),"",_xlfn.LET(_xlpm.m,MIN(I6,MAX(0,DATEDIF(E6,MIN(TODAY(),F6),"m")+1)),_xlpm.rm,(1+G6/4)^(1/3)-1,IF(_xlpm.rm=0,D6*_xlpm.m,D6*((1+_xlpm.rm)^_xlpm.m-1)/_xlpm.rm))) -> 243306.05 | M6: =IF(OR(D6="",I6="",G6=""),"",_xlfn.LET(_xlpm.rm,(1+G6/4)^(1/3)-1,IF(_xlpm.rm=0,D6*I6,D6*((1+_xlpm.rm)^I6-1)/_xlpm.rm))) -> 537413.5 | N6: =IF(OR(L6="",J6=""),"",L6-J6) -> 3306.0499 | O6: =IF(A6="","",IF(OR(E6="",F6=""),"Details Required",IF(TODAY()<E6,"Upcoming",IF(TODAY()>=F6,"Matured","Active")))) -> Active

Sheet Bonds
A1: BOND REGISTER
A2: Track purchases, coupon income, market value, daily movement, and total return for Velan and Pavi.
A4: Owner | B4: Issuer | C4: ISIN / Bond ID | D4: Face Value | E4: Quantity | F4: Purchase Price | G4: Purchase Date | H4: Coupon Rate | I4: Coupon Frequency | J4: Next Coupon Date | K4: Maturity Date | L4: Previous Close | M4: Market Price | N4: Invested Value | O4: Current Value | P4: Accrued Coupon | Q4: PL (Today) | R4: PL (Total) | S4: Status
A5: Velan | N5: =IF(OR(E5="",F5=""),"",E5*F5) | O5: =IF(OR(E5="",M5=""),"",E5*M5) | P5: =IF(OR(D5="",E5="",H5="",I5="",J5=""),"",D5*E5*H5*MAX(0,1-(J5-TODAY())/(365/I5))) | Q5: =IF(OR(E5="",L5="",M5=""),"",(M5-L5)*E5) | R5: =IF(OR(N5="",O5=""),"",O5+IF(P5="",0,P5)-N5) | S5: =IF(A5="","",IF(K5="","Details Required",IF(TODAY()>=K5,"Matured","Active"))) -> Details Required
A6: Pavi | N6: =IF(OR(E6="",F6=""),"",E6*F6) | O6: =IF(OR(E6="",M6=""),"",E6*M6) | P6: =IF(OR(D6="",E6="",H6="",I6="",J6=""),"",D6*E6*H6*MAX(0,1-(J6-TODAY())/(365/I6))) | Q6: =IF(OR(E6="",L6="",M6=""),"",(M6-L6)*E6) | R6: =IF(OR(N6="",O6=""),"",O6+IF(P6="",0,P6)-N6) | S6: =IF(A6="","",IF(K6="","Details Required",IF(TODAY()>=K6,"Matured","Active"))) -> Details Required
